document_insighter/__init__.py
document_insighter/api_client.py
document_insighter/exceptions.py
document_insighter/helpers.py
document_insighter/model.py
document_insighter-0.0.11.dist-info/METADATA
document_insighter-0.0.11.dist-info/WHEEL
document_insighter-0.0.11.dist-info/top_level.txt
document_insighter-0.0.11.dist-info/RECORD
