Metadata-Version: 2.1
Name: document-insighter
Version: 0.0.11
Summary: Document Insighter Python Client
Home-page: https://github.com/deepsite/document-insighter-python
Author: Wang Kai
Author-email: wangkai@godeepsite.com
License: MIT
Project-URL: Bug Tracker, https://github.com/deepsite/document-insighter-python/issues
Requires-Dist: requests (==2.31.0)
Requires-Dist: requests-oauthlib (==1.3.1)
Requires-Dist: dataclasses-json (==0.5.7)
Requires-Dist: polling2 (==0.5.0)
